README
setup.py
dml/__init__.py
dml/dml.py
dml.egg-info/PKG-INFO
dml.egg-info/SOURCES.txt
dml.egg-info/dependency_links.txt
dml.egg-info/requires.txt
dml.egg-info/top_level.txt