Metadata-Version: 1.0
Name: dml
Version: 0.0.13.0
Summary: Common functionalities for building Data Mechanics platform components.
Home-page: http://datamechanics.org
Author: Andrei Lapets
Author-email: a@lapets.io
License: MIT License
Platform: UNKNOWN
